djinni/__init__.py
djinni/djinni.py
python_djinni-0.4.0.dist-info/licenses/LICENSE
python_djinni-0.4.0.dist-info/METADATA
python_djinni-0.4.0.dist-info/WHEEL
python_djinni-0.4.0.dist-info/top_level.txt
python_djinni-0.4.0.dist-info/RECORD
