Metadata-Version: 2.4
Name: python-djinni
Version: 0.4.0
Summary: dependency injection for python
Home-page: https://github.com/robot-pizza/djinni-python
Author: robot.pizza
Author-email: robot.pizza@mightyheave.com
License: GNU General Public License v3 (GPLv3)
Classifier: Programming Language :: Python :: 3
Classifier: License :: OSI Approved :: GNU General Public License v3 (GPLv3)
Classifier: Operating System :: OS Independent
Requires-Python: >=3.8
License-File: LICENSE
Dynamic: license-file
